{"headings":["oa11cd","lsoa11cd","msoa11cd","ladcd","lsoa11nm","msoa11nm","ladnm","ladnmw"],"values":[["E00114714","E00167854",""],["E01022564","E01022543",""],["E02004694","E02004681",""],["E07000084",""],["Basingstoke and Deane 020C","Basingstoke and Deane 007F",""],["Basingstoke and Deane 020","Basingstoke and Deane 007",""],["Basingstoke and Deane",""],[""]],"data":{"RG28 9AA":[0,0,0,0,0,0,0,0],"RG28 9AB":[0,0,0,0,0,0,0,0],"RG28 9AD":[0,0,0,0,0,0,0,0],"RG28 9AE":[0,0,0,0,0,0,0,0],"RG28 9AF":[0,0,0,0,0,0,0,0],"RG28 9AG":[0,0,0,0,0,0,0,0],"RG28 9AH":[0,0,0,0,0,0,0,0],"RG28 9AJ":[0,0,0,0,0,0,0,0],"RG28 9AL":[0,0,0,0,0,0,0,0],"RG28 9AN":[0,0,0,0,0,0,0,0],"RG28 9AP":[0,0,0,0,0,0,0,0],"RG28 9AQ":[1,1,1,0,1,1,0,0],"RG28 9AR":[1,1,1,0,1,1,0,0],"RG28 9AS":[1,1,1,0,1,1,0,0],"RG28 9ZZ":[2,2,2,1,2,2,1,0]}}