{"headings":["oa11cd","lsoa11cd","msoa11cd","ladcd","lsoa11nm","msoa11nm","ladnm","ladnmw"],"values":[["S00126397","S00126398","S00126399","S00126402","S00126400","S00126401","S00126218","S00126108","S00126451"],["S01011851","S01011848","S01011869"],["S02002222","S02002226"],["S12000048"],["Muthill, Greenloaning and Gleneagles - 05","Muthill, Greenloaning and Gleneagles - 02","Crieff South - 04"],["Muthill, Greenloaning and Gleneagle","Crieff South"],["Perth and Kinross"],[""]],"data":{"PH5 2AA":[0,0,0,0,0,0,0,0],"PH5 2AB":[1,0,0,0,0,0,0,0],"PH5 2AD":[0,0,0,0,0,0,0,0],"PH5 2AE":[0,0,0,0,0,0,0,0],"PH5 2AF":[0,0,0,0,0,0,0,0],"PH5 2AG":[2,0,0,0,0,0,0,0],"PH5 2AH":[3,0,0,0,0,0,0,0],"PH5 2AJ":[0,0,0,0,0,0,0,0],"PH5 2AL":[0,0,0,0,0,0,0,0],"PH5 2AN":[4,0,0,0,0,0,0,0],"PH5 2AP":[4,0,0,0,0,0,0,0],"PH5 2AQ":[3,0,0,0,0,0,0,0],"PH5 2AR":[1,0,0,0,0,0,0,0],"PH5 2AS":[5,0,0,0,0,0,0,0],"PH5 2AT":[5,0,0,0,0,0,0,0],"PH5 2AU":[1,0,0,0,0,0,0,0],"PH5 2AW":[1,0,0,0,0,0,0,0],"PH5 2AX":[5,0,0,0,0,0,0,0],"PH5 2AY":[4,0,0,0,0,0,0,0],"PH5 2AZ":[6,0,0,0,0,0,0,0],"PH5 2BA":[6,0,0,0,0,0,0,0],"PH5 2BB":[6,0,0,0,0,0,0,0],"PH5 2BD":[6,0,0,0,0,0,0,0],"PH5 2BE":[6,0,0,0,0,0,0,0],"PH5 2BG":[6,0,0,0,0,0,0,0],"PH5 2BH":[6,0,0,0,0,0,0,0],"PH5 2BJ":[6,0,0,0,0,0,0,0],"PH5 2BL":[6,0,0,0,0,0,0,0],"PH5 2BN":[6,0,0,0,0,0,0,0],"PH5 2BP":[6,0,0,0,0,0,0,0],"PH5 2BS":[6,0,0,0,0,0,0,0],"PH5 2BT":[6,0,0,0,0,0,0,0],"PH5 2BU":[6,0,0,0,0,0,0,0],"PH5 2BW":[6,0,0,0,0,0,0,0],"PH5 2BX":[6,0,0,0,0,0,0,0],"PH5 2BY":[6,0,0,0,0,0,0,0],"PH5 2BZ":[6,0,0,0,0,0,0,0],"PH5 2DA":[7,1,0,0,1,0,0,0],"PH5 2DB":[7,1,0,0,1,0,0,0],"PH5 2DD":[7,1,0,0,1,0,0,0],"PH5 2DE":[7,1,0,0,1,0,0,0],"PH5 2DF":[7,1,0,0,1,0,0,0],"PH5 2DG":[4,0,0,0,0,0,0,0],"PH5 2YA":[6,0,0,0,0,0,0,0],"PH5 2YB":[8,2,1,0,2,1,0,0],"PH5 2YD":[0,0,0,0,0,0,0,0]}}