{"headings":["oa11cd","lsoa11cd","msoa11cd","ladcd","lsoa11nm","msoa11nm","ladnm","ladnmw"],"values":[["E00160796"],["E01031528"],["E02006574"],["E07000225"],["Chichester 014G"],["Chichester 014"],["Chichester"],[""]],"data":{"PO20 4AA":[0,0,0,0,0,0,0,0],"PO20 4AB":[0,0,0,0,0,0,0,0],"PO20 4AD":[0,0,0,0,0,0,0,0],"PO20 4AE":[0,0,0,0,0,0,0,0],"PO20 4AF":[0,0,0,0,0,0,0,0],"PO20 4AG":[0,0,0,0,0,0,0,0],"PO20 4AH":[0,0,0,0,0,0,0,0],"PO20 4AJ":[0,0,0,0,0,0,0,0],"PO20 4AL":[0,0,0,0,0,0,0,0],"PO20 4AN":[0,0,0,0,0,0,0,0],"PO20 4AP":[0,0,0,0,0,0,0,0],"PO20 4AQ":[0,0,0,0,0,0,0,0],"PO20 4AR":[0,0,0,0,0,0,0,0],"PO20 4AS":[0,0,0,0,0,0,0,0],"PO20 4AT":[0,0,0,0,0,0,0,0],"PO20 4AU":[0,0,0,0,0,0,0,0],"PO20 4AW":[0,0,0,0,0,0,0,0],"PO20 4AX":[0,0,0,0,0,0,0,0],"PO20 4AY":[0,0,0,0,0,0,0,0],"PO20 4AZ":[0,0,0,0,0,0,0,0]}}