{"headings":["oa11cd","lsoa11cd","msoa11cd","ladcd","lsoa11nm","msoa11nm","ladnm","ladnmw"],"values":[["E00087436"],["E01017312"],["E02003592"],["E06000046"],["Isle of Wight 012A"],["Isle of Wight 012"],["Isle of Wight"],[""]],"data":{"PO40 0AA":[0,0,0,0,0,0,0,0],"PO40 0AB":[0,0,0,0,0,0,0,0],"PO40 0AD":[0,0,0,0,0,0,0,0],"PO40 0AE":[0,0,0,0,0,0,0,0],"PO40 0AF":[0,0,0,0,0,0,0,0],"PO40 0AG":[0,0,0,0,0,0,0,0],"PO40 0AH":[0,0,0,0,0,0,0,0],"PO40 0AJ":[0,0,0,0,0,0,0,0],"PO40 0AL":[0,0,0,0,0,0,0,0],"PO40 0AN":[0,0,0,0,0,0,0,0],"PO40 0AP":[0,0,0,0,0,0,0,0],"PO40 0AQ":[0,0,0,0,0,0,0,0],"PO40 0AR":[0,0,0,0,0,0,0,0],"PO40 0AS":[0,0,0,0,0,0,0,0]}}