{"headings":["oa11cd","lsoa11cd","msoa11cd","ladcd","lsoa11nm","msoa11nm","ladnm","ladnmw"],"values":[["","E00015315"],["","E01003039"],["","E02000630"],["","E09000022"],["","Lambeth 013C"],["","Lambeth 013"],["","Lambeth"],[""]],"data":{"SW3 9AA":[0,0,0,0,0,0,0,0],"SW3 9AB":[0,0,0,0,0,0,0,0],"SW3 9AD":[0,0,0,0,0,0,0,0],"SW3 9AE":[0,0,0,0,0,0,0,0],"SW3 9AF":[0,0,0,0,0,0,0,0],"SW3 9AG":[0,0,0,0,0,0,0,0],"SW3 9AH":[0,0,0,0,0,0,0,0],"SW3 9AJ":[0,0,0,0,0,0,0,0],"SW3 9AL":[0,0,0,0,0,0,0,0],"SW3 9AN":[0,0,0,0,0,0,0,0],"SW3 9AP":[0,0,0,0,0,0,0,0],"SW3 9AQ":[0,0,0,0,0,0,0,0],"SW3 9AR":[0,0,0,0,0,0,0,0],"SW3 9AS":[1,1,1,1,1,1,1,0],"SW3 9AT":[1,1,1,1,1,1,1,0],"SW3 9AU":[1,1,1,1,1,1,1,0],"SW3 9AW":[1,1,1,1,1,1,1,0],"SW3 9AX":[0,0,0,0,0,0,0,0],"SW3 9AY":[1,1,1,1,1,1,1,0],"SW3 9AZ":[0,0,0,0,0,0,0,0],"SW3 9BA":[0,0,0,0,0,0,0,0],"SW3 9BB":[1,1,1,1,1,1,1,0],"SW3 9BD":[0,0,0,0,0,0,0,0],"SW3 9BE":[0,0,0,0,0,0,0,0],"SW3 9BF":[0,0,0,0,0,0,0,0],"SW3 9BG":[1,1,1,1,1,1,1,0],"SW3 9BH":[1,1,1,1,1,1,1,0],"SW3 9BJ":[0,0,0,0,0,0,0,0],"SW3 9BL":[0,0,0,0,0,0,0,0],"SW3 9BN":[0,0,0,0,0,0,0,0],"SW3 9BP":[0,0,0,0,0,0,0,0],"SW3 9BQ":[0,0,0,0,0,0,0,0],"SW3 9BR":[1,1,1,1,1,1,1,0],"SW3 9BS":[1,1,1,1,1,1,1,0],"SW3 9BT":[1,1,1,1,1,1,1,0],"SW3 9BU":[1,1,1,1,1,1,1,0],"SW3 9BW":[1,1,1,1,1,1,1,0],"SW3 9BX":[0,0,0,0,0,0,0,0],"SW3 9BY":[1,1,1,1,1,1,1,0],"SW3 9BZ":[1,1,1,1,1,1,1,0],"SW3 9DA":[1,1,1,1,1,1,1,0],"SW3 9DB":[0,0,0,0,0,0,0,0],"SW3 9DD":[1,1,1,1,1,1,1,0],"SW3 9DE":[0,0,0,0,0,0,0,0],"SW3 9DF":[1,1,1,1,1,1,1,0],"SW3 9DG":[1,1,1,1,1,1,1,0],"SW3 9DH":[0,0,0,0,0,0,0,0],"SW3 9DJ":[1,1,1,1,1,1,1,0],"SW3 9DL":[1,1,1,1,1,1,1,0],"SW3 9DN":[1,1,1,1,1,1,1,0],"SW3 9DP":[1,1,1,1,1,1,1,0],"SW3 9DQ":[1,1,1,1,1,1,1,0],"SW3 9DR":[1,1,1,1,1,1,1,0],"SW3 9DS":[1,1,1,1,1,1,1,0],"SW3 9DT":[1,1,1,1,1,1,1,0],"SW3 9DU":[1,1,1,1,1,1,1,0],"SW3 9DW":[1,1,1,1,1,1,1,0],"SW3 9DX":[1,1,1,1,1,1,1,0],"SW3 9DY":[1,1,1,1,1,1,1,0],"SW3 9DZ":[1,1,1,1,1,1,1,0],"SW3 9EA":[1,1,1,1,1,1,1,0],"SW3 9EB":[1,1,1,1,1,1,1,0],"SW3 9ED":[1,1,1,1,1,1,1,0],"SW3 9EE":[1,1,1,1,1,1,1,0],"SW3 9EF":[1,1,1,1,1,1,1,0],"SW3 9EG":[1,1,1,1,1,1,1,0],"SW3 9EH":[1,1,1,1,1,1,1,0],"SW3 9EJ":[1,1,1,1,1,1,1,0],"SW3 9EL":[1,1,1,1,1,1,1,0],"SW3 9EN":[1,1,1,1,1,1,1,0],"SW3 9EP":[1,1,1,1,1,1,1,0],"SW3 9EQ":[1,1,1,1,1,1,1,0],"SW3 9ER":[1,1,1,1,1,1,1,0],"SW3 9ES":[1,1,1,1,1,1,1,0],"SW3 9ET":[1,1,1,1,1,1,1,0],"SW3 9EU":[1,1,1,1,1,1,1,0],"SW3 9EW":[1,1,1,1,1,1,1,0],"SW3 9EX":[1,1,1,1,1,1,1,0],"SW3 9EY":[1,1,1,1,1,1,1,0],"SW3 9EZ":[1,1,1,1,1,1,1,0],"SW3 9FA":[1,1,1,1,1,1,1,0],"SW3 9FB":[1,1,1,1,1,1,1,0],"SW3 9FD":[1,1,1,1,1,1,1,0],"SW3 9FE":[1,1,1,1,1,1,1,0],"SW3 9FF":[1,1,1,1,1,1,1,0],"SW3 9FG":[1,1,1,1,1,1,1,0],"SW3 9FH":[1,1,1,1,1,1,1,0],"SW3 9FJ":[1,1,1,1,1,1,1,0],"SW3 9FL":[1,1,1,1,1,1,1,0],"SW3 9FN":[1,1,1,1,1,1,1,0],"SW3 9FP":[1,1,1,1,1,1,1,0],"SW3 9FQ":[1,1,1,1,1,1,1,0],"SW3 9FR":[1,1,1,1,1,1,1,0],"SW3 9FS":[1,1,1,1,1,1,1,0],"SW3 9FT":[1,1,1,1,1,1,1,0],"SW3 9FU":[1,1,1,1,1,1,1,0],"SW3 9FW":[1,1,1,1,1,1,1,0],"SW3 9FX":[1,1,1,1,1,1,1,0],"SW3 9FY":[1,1,1,1,1,1,1,0],"SW3 9FZ":[1,1,1,1,1,1,1,0],"SW3 9GA":[1,1,1,1,1,1,1,0],"SW3 9GB":[1,1,1,1,1,1,1,0],"SW3 9GD":[1,1,1,1,1,1,1,0]}}