{"headings":["oa11cd","lsoa11cd","msoa11cd","ladcd","lsoa11nm","msoa11nm","ladnm","ladnmw"],"values":[["E00088616","E00171396"],["E01017555","E01017575"],["E02003639","E02003643"],["E06000056"],["Central Bedfordshire 021A","Central Bedfordshire 024C"],["Central Bedfordshire 021","Central Bedfordshire 024"],["Central Bedfordshire"],[""]],"data":{"LU95 1AA":[0,0,0,0,0,0,0,0],"LU95 1AB":[0,0,0,0,0,0,0,0],"LU95 1AD":[0,0,0,0,0,0,0,0],"LU95 1AE":[1,1,1,0,1,1,0,0],"LU95 1AF":[0,0,0,0,0,0,0,0],"LU95 1AG":[0,0,0,0,0,0,0,0],"LU95 1AH":[0,0,0,0,0,0,0,0],"LU95 1AJ":[0,0,0,0,0,0,0,0],"LU95 1AL":[0,0,0,0,0,0,0,0],"LU95 1AN":[0,0,0,0,0,0,0,0],"LU95 1AP":[0,0,0,0,0,0,0,0],"LU95 1AQ":[0,0,0,0,0,0,0,0],"LU95 1AR":[0,0,0,0,0,0,0,0],"LU95 1AS":[0,0,0,0,0,0,0,0],"LU95 1AT":[0,0,0,0,0,0,0,0],"LU95 1AU":[0,0,0,0,0,0,0,0],"LU95 1AW":[0,0,0,0,0,0,0,0],"LU95 1AX":[0,0,0,0,0,0,0,0],"LU95 1AY":[1,1,1,0,1,1,0,0],"LU95 1AZ":[0,0,0,0,0,0,0,0],"LU95 1BB":[1,1,1,0,1,1,0,0],"LU95 1BD":[1,1,1,0,1,1,0,0],"LU95 1BE":[1,1,1,0,1,1,0,0],"LU95 1LH":[0,0,0,0,0,0,0,0]}}