{"headings":["oa11cd","lsoa11cd","msoa11cd","ladcd","lsoa11nm","msoa11nm","ladnm","ladnmw"],"values":[["S00129024","S00129022","S00129025","S00129023"],["S01012387"],["S02002322"],["S12000027"],["Shetland South - 01"],["Shetland South"],["Shetland Islands"],[""]],"data":{"ZE3 9JJ":[0,0,0,0,0,0,0,0],"ZE3 9JL":[0,0,0,0,0,0,0,0],"ZE3 9JN":[1,0,0,0,0,0,0,0],"ZE3 9JP":[1,0,0,0,0,0,0,0],"ZE3 9JR":[2,0,0,0,0,0,0,0],"ZE3 9JS":[3,0,0,0,0,0,0,0],"ZE3 9JT":[1,0,0,0,0,0,0,0],"ZE3 9JU":[0,0,0,0,0,0,0,0],"ZE3 9JW":[1,0,0,0,0,0,0,0],"ZE3 9JX":[1,0,0,0,0,0,0,0],"ZE3 9JY":[2,0,0,0,0,0,0,0],"ZE3 9JZ":[2,0,0,0,0,0,0,0],"ZE3 9XP":[0,0,0,0,0,0,0,0]}}