{"headings":["oa11cd","lsoa11cd","msoa11cd","ladcd","lsoa11nm","msoa11nm","ladnm","ladnmw"],"values":[["W00003813"],["W01000709"],["W02000145"],["W06000010"],["Carmarthenshire 004D"],["Carmarthenshire 004"],["Carmarthenshire"],["Sir Gaerfyrddin"]],"data":{"SA19 0AA":[0,0,0,0,0,0,0,0],"SA19 0AB":[0,0,0,0,0,0,0,0],"SA19 0AD":[0,0,0,0,0,0,0,0],"SA19 0AE":[0,0,0,0,0,0,0,0],"SA19 0AF":[0,0,0,0,0,0,0,0],"SA19 0AG":[0,0,0,0,0,0,0,0],"SA19 0AH":[0,0,0,0,0,0,0,0],"SA19 0AJ":[0,0,0,0,0,0,0,0],"SA19 0AL":[0,0,0,0,0,0,0,0],"SA19 0AN":[0,0,0,0,0,0,0,0],"SA19 0AP":[0,0,0,0,0,0,0,0],"SA19 0AQ":[0,0,0,0,0,0,0,0],"SA19 0AR":[0,0,0,0,0,0,0,0],"SA19 0AS":[0,0,0,0,0,0,0,0],"SA19 0AT":[0,0,0,0,0,0,0,0],"SA19 0AU":[0,0,0,0,0,0,0,0],"SA19 0AW":[0,0,0,0,0,0,0,0],"SA19 0AX":[0,0,0,0,0,0,0,0],"SA19 0AY":[0,0,0,0,0,0,0,0]}}