{"headings":["oa11cd","lsoa11cd","msoa11cd","ladcd","lsoa11nm","msoa11nm","ladnm","ladnmw"],"values":[["E00097346","E00097347"],["E01019259"],["E02004007"],["E07000029"],["Copeland 008A"],["Copeland 008"],["Copeland"],[""]],"data":{"CA18 1BR":[0,0,0,0,0,0,0,0],"CA18 1RA":[0,0,0,0,0,0,0,0],"CA18 1RD":[0,0,0,0,0,0,0,0],"CA18 1RE":[0,0,0,0,0,0,0,0],"CA18 1RF":[0,0,0,0,0,0,0,0],"CA18 1RG":[0,0,0,0,0,0,0,0],"CA18 1RJ":[0,0,0,0,0,0,0,0],"CA18 1RL":[0,0,0,0,0,0,0,0],"CA18 1RN":[0,0,0,0,0,0,0,0],"CA18 1RQ":[0,0,0,0,0,0,0,0],"CA18 1RR":[1,0,0,0,0,0,0,0],"CA18 1RS":[1,0,0,0,0,0,0,0],"CA18 1RT":[0,0,0,0,0,0,0,0],"CA18 1RW":[0,0,0,0,0,0,0,0],"CA18 1SD":[0,0,0,0,0,0,0,0],"CA18 1SE":[0,0,0,0,0,0,0,0],"CA18 1SF":[0,0,0,0,0,0,0,0],"CA18 1SG":[0,0,0,0,0,0,0,0],"CA18 1SH":[0,0,0,0,0,0,0,0],"CA18 1SJ":[0,0,0,0,0,0,0,0],"CA18 1SL":[0,0,0,0,0,0,0,0],"CA18 1SN":[0,0,0,0,0,0,0,0],"CA18 1SP":[0,0,0,0,0,0,0,0],"CA18 1SQ":[0,0,0,0,0,0,0,0],"CA18 1SR":[0,0,0,0,0,0,0,0],"CA18 1ST":[0,0,0,0,0,0,0,0],"CA18 1SU":[0,0,0,0,0,0,0,0],"CA18 1SW":[0,0,0,0,0,0,0,0]}}