{"headings":["oa11cd","lsoa11cd","msoa11cd","ladcd","lsoa11nm","msoa11nm","ladnm","ladnmw"],"values":[["L99999999"],["L99999999"],["L99999999"],["L99999999"],["(pseudo) Channel Islands"],["(pseudo) Channel Islands"],["Pseudo (Channel Islands)"],[""]],"data":{"GY1 1AA":[0,0,0,0,0,0,0,0],"GY1 1AB":[0,0,0,0,0,0,0,0],"GY1 1AD":[0,0,0,0,0,0,0,0],"GY1 1AE":[0,0,0,0,0,0,0,0],"GY1 1AF":[0,0,0,0,0,0,0,0],"GY1 1AG":[0,0,0,0,0,0,0,0],"GY1 1AH":[0,0,0,0,0,0,0,0],"GY1 1AJ":[0,0,0,0,0,0,0,0],"GY1 1AL":[0,0,0,0,0,0,0,0],"GY1 1AN":[0,0,0,0,0,0,0,0],"GY1 1AP":[0,0,0,0,0,0,0,0],"GY1 1AQ":[0,0,0,0,0,0,0,0],"GY1 1AR":[0,0,0,0,0,0,0,0],"GY1 1AT":[0,0,0,0,0,0,0,0],"GY1 1AU":[0,0,0,0,0,0,0,0],"GY1 1AW":[0,0,0,0,0,0,0,0],"GY1 1AX":[0,0,0,0,0,0,0,0],"GY1 1AY":[0,0,0,0,0,0,0,0],"GY1 1AZ":[0,0,0,0,0,0,0,0],"GY1 1BA":[0,0,0,0,0,0,0,0],"GY1 1BB":[0,0,0,0,0,0,0,0],"GY1 1BD":[0,0,0,0,0,0,0,0],"GY1 1BE":[0,0,0,0,0,0,0,0],"GY1 1BF":[0,0,0,0,0,0,0,0],"GY1 1BG":[0,0,0,0,0,0,0,0],"GY1 1BH":[0,0,0,0,0,0,0,0],"GY1 1BJ":[0,0,0,0,0,0,0,0],"GY1 1BP":[0,0,0,0,0,0,0,0],"GY1 1BQ":[0,0,0,0,0,0,0,0],"GY1 1BR":[0,0,0,0,0,0,0,0],"GY1 1BS":[0,0,0,0,0,0,0,0],"GY1 1BT":[0,0,0,0,0,0,0,0],"GY1 1BU":[0,0,0,0,0,0,0,0],"GY1 1BX":[0,0,0,0,0,0,0,0],"GY1 1BY":[0,0,0,0,0,0,0,0],"GY1 1BZ":[0,0,0,0,0,0,0,0],"GY1 1DA":[0,0,0,0,0,0,0,0],"GY1 1DB":[0,0,0,0,0,0,0,0],"GY1 1DD":[0,0,0,0,0,0,0,0],"GY1 1DE":[0,0,0,0,0,0,0,0],"GY1 1DF":[0,0,0,0,0,0,0,0],"GY1 1DG":[0,0,0,0,0,0,0,0],"GY1 1DH":[0,0,0,0,0,0,0,0],"GY1 1DJ":[0,0,0,0,0,0,0,0],"GY1 1DL":[0,0,0,0,0,0,0,0],"GY1 1DQ":[0,0,0,0,0,0,0,0],"GY1 1DR":[0,0,0,0,0,0,0,0],"GY1 1DU":[0,0,0,0,0,0,0,0],"GY1 1DX":[0,0,0,0,0,0,0,0],"GY1 1DY":[0,0,0,0,0,0,0,0],"GY1 1DZ":[0,0,0,0,0,0,0,0],"GY1 1EA":[0,0,0,0,0,0,0,0],"GY1 1EB":[0,0,0,0,0,0,0,0],"GY1 1ED":[0,0,0,0,0,0,0,0],"GY1 1EE":[0,0,0,0,0,0,0,0],"GY1 1EF":[0,0,0,0,0,0,0,0],"GY1 1EG":[0,0,0,0,0,0,0,0],"GY1 1EH":[0,0,0,0,0,0,0,0],"GY1 1EJ":[0,0,0,0,0,0,0,0],"GY1 1EL":[0,0,0,0,0,0,0,0],"GY1 1EN":[0,0,0,0,0,0,0,0],"GY1 1EP":[0,0,0,0,0,0,0,0],"GY1 1EQ":[0,0,0,0,0,0,0,0],"GY1 1ER":[0,0,0,0,0,0,0,0],"GY1 1ES":[0,0,0,0,0,0,0,0],"GY1 1ET":[0,0,0,0,0,0,0,0],"GY1 1EU":[0,0,0,0,0,0,0,0],"GY1 1EW":[0,0,0,0,0,0,0,0],"GY1 1EX":[0,0,0,0,0,0,0,0],"GY1 1EY":[0,0,0,0,0,0,0,0],"GY1 1EZ":[0,0,0,0,0,0,0,0],"GY1 1FB":[0,0,0,0,0,0,0,0],"GY1 1FD":[0,0,0,0,0,0,0,0],"GY1 1FE":[0,0,0,0,0,0,0,0],"GY1 1FF":[0,0,0,0,0,0,0,0],"GY1 1FG":[0,0,0,0,0,0,0,0],"GY1 1FH":[0,0,0,0,0,0,0,0],"GY1 1FJ":[0,0,0,0,0,0,0,0],"GY1 1FL":[0,0,0,0,0,0,0,0],"GY1 1FN":[0,0,0,0,0,0,0,0],"GY1 1FP":[0,0,0,0,0,0,0,0],"GY1 1FQ":[0,0,0,0,0,0,0,0],"GY1 1FR":[0,0,0,0,0,0,0,0],"GY1 1FS":[0,0,0,0,0,0,0,0],"GY1 1FT":[0,0,0,0,0,0,0,0],"GY1 1FW":[0,0,0,0,0,0,0,0],"GY1 1FX":[0,0,0,0,0,0,0,0],"GY1 1FY":[0,0,0,0,0,0,0,0],"GY1 1FZ":[0,0,0,0,0,0,0,0],"GY1 1GA":[0,0,0,0,0,0,0,0],"GY1 1GB":[0,0,0,0,0,0,0,0],"GY1 1GD":[0,0,0,0,0,0,0,0],"GY1 1GE":[0,0,0,0,0,0,0,0],"GY1 1GF":[0,0,0,0,0,0,0,0],"GY1 1GG":[0,0,0,0,0,0,0,0],"GY1 1GH":[0,0,0,0,0,0,0,0],"GY1 1GL":[0,0,0,0,0,0,0,0],"GY1 1GP":[0,0,0,0,0,0,0,0],"GY1 1GQ":[0,0,0,0,0,0,0,0],"GY1 1GR":[0,0,0,0,0,0,0,0],"GY1 1GS":[0,0,0,0,0,0,0,0],"GY1 1GX":[0,0,0,0,0,0,0,0],"GY1 1GZ":[0,0,0,0,0,0,0,0],"GY1 1HB":[0,0,0,0,0,0,0,0],"GY1 1HD":[0,0,0,0,0,0,0,0],"GY1 1HE":[0,0,0,0,0,0,0,0],"GY1 1HF":[0,0,0,0,0,0,0,0],"GY1 1HG":[0,0,0,0,0,0,0,0],"GY1 1HH":[0,0,0,0,0,0,0,0],"GY1 1HJ":[0,0,0,0,0,0,0,0],"GY1 1HL":[0,0,0,0,0,0,0,0],"GY1 1HN":[0,0,0,0,0,0,0,0],"GY1 1HP":[0,0,0,0,0,0,0,0],"GY1 1HQ":[0,0,0,0,0,0,0,0],"GY1 1HR":[0,0,0,0,0,0,0,0],"GY1 1HS":[0,0,0,0,0,0,0,0],"GY1 1HT":[0,0,0,0,0,0,0,0],"GY1 1HU":[0,0,0,0,0,0,0,0],"GY1 1HW":[0,0,0,0,0,0,0,0],"GY1 1HX":[0,0,0,0,0,0,0,0],"GY1 1HY":[0,0,0,0,0,0,0,0],"GY1 1HZ":[0,0,0,0,0,0,0,0],"GY1 1JA":[0,0,0,0,0,0,0,0],"GY1 1JB":[0,0,0,0,0,0,0,0],"GY1 1JD":[0,0,0,0,0,0,0,0],"GY1 1JE":[0,0,0,0,0,0,0,0],"GY1 1JF":[0,0,0,0,0,0,0,0],"GY1 1JG":[0,0,0,0,0,0,0,0],"GY1 1JH":[0,0,0,0,0,0,0,0],"GY1 1JJ":[0,0,0,0,0,0,0,0],"GY1 1JL":[0,0,0,0,0,0,0,0],"GY1 1JP":[0,0,0,0,0,0,0,0],"GY1 1JQ":[0,0,0,0,0,0,0,0],"GY1 1JR":[0,0,0,0,0,0,0,0],"GY1 1JS":[0,0,0,0,0,0,0,0],"GY1 1JT":[0,0,0,0,0,0,0,0],"GY1 1JU":[0,0,0,0,0,0,0,0],"GY1 1JX":[0,0,0,0,0,0,0,0],"GY1 1JZ":[0,0,0,0,0,0,0,0],"GY1 1LA":[0,0,0,0,0,0,0,0],"GY1 1LB":[0,0,0,0,0,0,0,0],"GY1 1LD":[0,0,0,0,0,0,0,0],"GY1 1LE":[0,0,0,0,0,0,0,0],"GY1 1LF":[0,0,0,0,0,0,0,0],"GY1 1LG":[0,0,0,0,0,0,0,0],"GY1 1LH":[0,0,0,0,0,0,0,0],"GY1 1LJ":[0,0,0,0,0,0,0,0],"GY1 1LL":[0,0,0,0,0,0,0,0],"GY1 1LN":[0,0,0,0,0,0,0,0],"GY1 1LP":[0,0,0,0,0,0,0,0],"GY1 1LQ":[0,0,0,0,0,0,0,0],"GY1 1LR":[0,0,0,0,0,0,0,0],"GY1 1LS":[0,0,0,0,0,0,0,0],"GY1 1LT":[0,0,0,0,0,0,0,0],"GY1 1LU":[0,0,0,0,0,0,0,0],"GY1 1LW":[0,0,0,0,0,0,0,0],"GY1 1LX":[0,0,0,0,0,0,0,0],"GY1 1LY":[0,0,0,0,0,0,0,0],"GY1 1LZ":[0,0,0,0,0,0,0,0],"GY1 1NA":[0,0,0,0,0,0,0,0],"GY1 1NB":[0,0,0,0,0,0,0,0],"GY1 1ND":[0,0,0,0,0,0,0,0],"GY1 1NE":[0,0,0,0,0,0,0,0],"GY1 1NF":[0,0,0,0,0,0,0,0],"GY1 1NG":[0,0,0,0,0,0,0,0],"GY1 1NH":[0,0,0,0,0,0,0,0],"GY1 1NJ":[0,0,0,0,0,0,0,0],"GY1 1NL":[0,0,0,0,0,0,0,0],"GY1 1NN":[0,0,0,0,0,0,0,0],"GY1 1NQ":[0,0,0,0,0,0,0,0],"GY1 1NR":[0,0,0,0,0,0,0,0],"GY1 1NS":[0,0,0,0,0,0,0,0],"GY1 1NT":[0,0,0,0,0,0,0,0],"GY1 1NU":[0,0,0,0,0,0,0,0],"GY1 1NW":[0,0,0,0,0,0,0,0],"GY1 1NX":[0,0,0,0,0,0,0,0],"GY1 1NY":[0,0,0,0,0,0,0,0],"GY1 1NZ":[0,0,0,0,0,0,0,0],"GY1 1PA":[0,0,0,0,0,0,0,0],"GY1 1PB":[0,0,0,0,0,0,0,0],"GY1 1PD":[0,0,0,0,0,0,0,0],"GY1 1PE":[0,0,0,0,0,0,0,0],"GY1 1PF":[0,0,0,0,0,0,0,0],"GY1 1PG":[0,0,0,0,0,0,0,0],"GY1 1PH":[0,0,0,0,0,0,0,0],"GY1 1PJ":[0,0,0,0,0,0,0,0],"GY1 1PL":[0,0,0,0,0,0,0,0],"GY1 1PN":[0,0,0,0,0,0,0,0],"GY1 1PQ":[0,0,0,0,0,0,0,0],"GY1 1PS":[0,0,0,0,0,0,0,0],"GY1 1PT":[0,0,0,0,0,0,0,0],"GY1 1PU":[0,0,0,0,0,0,0,0],"GY1 1PX":[0,0,0,0,0,0,0,0],"GY1 1PY":[0,0,0,0,0,0,0,0],"GY1 1PZ":[0,0,0,0,0,0,0,0],"GY1 1QA":[0,0,0,0,0,0,0,0],"GY1 1QB":[0,0,0,0,0,0,0,0],"GY1 1QD":[0,0,0,0,0,0,0,0],"GY1 1QE":[0,0,0,0,0,0,0,0],"GY1 1QF":[0,0,0,0,0,0,0,0],"GY1 1QG":[0,0,0,0,0,0,0,0],"GY1 1QH":[0,0,0,0,0,0,0,0],"GY1 1QJ":[0,0,0,0,0,0,0,0],"GY1 1QL":[0,0,0,0,0,0,0,0],"GY1 1QN":[0,0,0,0,0,0,0,0],"GY1 1QP":[0,0,0,0,0,0,0,0],"GY1 1QQ":[0,0,0,0,0,0,0,0],"GY1 1QR":[0,0,0,0,0,0,0,0],"GY1 1QS":[0,0,0,0,0,0,0,0],"GY1 1QT":[0,0,0,0,0,0,0,0],"GY1 1QU":[0,0,0,0,0,0,0,0],"GY1 1QW":[0,0,0,0,0,0,0,0],"GY1 1RB":[0,0,0,0,0,0,0,0],"GY1 1RD":[0,0,0,0,0,0,0,0],"GY1 1RE":[0,0,0,0,0,0,0,0],"GY1 1RF":[0,0,0,0,0,0,0,0],"GY1 1RG":[0,0,0,0,0,0,0,0],"GY1 1RH":[0,0,0,0,0,0,0,0],"GY1 1RJ":[0,0,0,0,0,0,0,0],"GY1 1RL":[0,0,0,0,0,0,0,0],"GY1 1RN":[0,0,0,0,0,0,0,0],"GY1 1RP":[0,0,0,0,0,0,0,0],"GY1 1RQ":[0,0,0,0,0,0,0,0],"GY1 1RR":[0,0,0,0,0,0,0,0],"GY1 1RS":[0,0,0,0,0,0,0,0],"GY1 1RT":[0,0,0,0,0,0,0,0],"GY1 1RU":[0,0,0,0,0,0,0,0],"GY1 1RW":[0,0,0,0,0,0,0,0],"GY1 1RX":[0,0,0,0,0,0,0,0],"GY1 1RY":[0,0,0,0,0,0,0,0],"GY1 1RZ":[0,0,0,0,0,0,0,0],"GY1 1SA":[0,0,0,0,0,0,0,0],"GY1 1SB":[0,0,0,0,0,0,0,0],"GY1 1SD":[0,0,0,0,0,0,0,0],"GY1 1SE":[0,0,0,0,0,0,0,0],"GY1 1SF":[0,0,0,0,0,0,0,0],"GY1 1SL":[0,0,0,0,0,0,0,0],"GY1 1SN":[0,0,0,0,0,0,0,0],"GY1 1SP":[0,0,0,0,0,0,0,0],"GY1 1SR":[0,0,0,0,0,0,0,0],"GY1 1SS":[0,0,0,0,0,0,0,0],"GY1 1ST":[0,0,0,0,0,0,0,0],"GY1 1SU":[0,0,0,0,0,0,0,0],"GY1 1SW":[0,0,0,0,0,0,0,0],"GY1 1SX":[0,0,0,0,0,0,0,0],"GY1 1SY":[0,0,0,0,0,0,0,0],"GY1 1SZ":[0,0,0,0,0,0,0,0],"GY1 1TA":[0,0,0,0,0,0,0,0],"GY1 1TB":[0,0,0,0,0,0,0,0],"GY1 1TD":[0,0,0,0,0,0,0,0],"GY1 1TE":[0,0,0,0,0,0,0,0],"GY1 1TF":[0,0,0,0,0,0,0,0],"GY1 1TG":[0,0,0,0,0,0,0,0],"GY1 1TH":[0,0,0,0,0,0,0,0],"GY1 1TJ":[0,0,0,0,0,0,0,0],"GY1 1TL":[0,0,0,0,0,0,0,0],"GY1 1TN":[0,0,0,0,0,0,0,0],"GY1 1TP":[0,0,0,0,0,0,0,0],"GY1 1TQ":[0,0,0,0,0,0,0,0],"GY1 1TR":[0,0,0,0,0,0,0,0],"GY1 1TS":[0,0,0,0,0,0,0,0],"GY1 1TT":[0,0,0,0,0,0,0,0],"GY1 1TU":[0,0,0,0,0,0,0,0],"GY1 1TW":[0,0,0,0,0,0,0,0],"GY1 1TX":[0,0,0,0,0,0,0,0],"GY1 1TY":[0,0,0,0,0,0,0,0],"GY1 1TZ":[0,0,0,0,0,0,0,0],"GY1 1UF":[0,0,0,0,0,0,0,0],"GY1 1UG":[0,0,0,0,0,0,0,0],"GY1 1UH":[0,0,0,0,0,0,0,0],"GY1 1UJ":[0,0,0,0,0,0,0,0],"GY1 1UL":[0,0,0,0,0,0,0,0],"GY1 1UN":[0,0,0,0,0,0,0,0],"GY1 1UP":[0,0,0,0,0,0,0,0],"GY1 1UQ":[0,0,0,0,0,0,0,0],"GY1 1UR":[0,0,0,0,0,0,0,0],"GY1 1US":[0,0,0,0,0,0,0,0],"GY1 1UT":[0,0,0,0,0,0,0,0],"GY1 1UU":[0,0,0,0,0,0,0,0],"GY1 1UW":[0,0,0,0,0,0,0,0],"GY1 1UX":[0,0,0,0,0,0,0,0],"GY1 1UY":[0,0,0,0,0,0,0,0],"GY1 1UZ":[0,0,0,0,0,0,0,0],"GY1 1WA":[0,0,0,0,0,0,0,0],"GY1 1WB":[0,0,0,0,0,0,0,0],"GY1 1WD":[0,0,0,0,0,0,0,0],"GY1 1WE":[0,0,0,0,0,0,0,0],"GY1 1WF":[0,0,0,0,0,0,0,0],"GY1 1WG":[0,0,0,0,0,0,0,0],"GY1 1WH":[0,0,0,0,0,0,0,0],"GY1 1WJ":[0,0,0,0,0,0,0,0],"GY1 1WL":[0,0,0,0,0,0,0,0],"GY1 1WN":[0,0,0,0,0,0,0,0],"GY1 1WP":[0,0,0,0,0,0,0,0],"GY1 1WQ":[0,0,0,0,0,0,0,0],"GY1 1WR":[0,0,0,0,0,0,0,0],"GY1 1WS":[0,0,0,0,0,0,0,0],"GY1 1WT":[0,0,0,0,0,0,0,0],"GY1 1WU":[0,0,0,0,0,0,0,0],"GY1 1WW":[0,0,0,0,0,0,0,0],"GY1 1WX":[0,0,0,0,0,0,0,0],"GY1 1WY":[0,0,0,0,0,0,0,0],"GY1 1WZ":[0,0,0,0,0,0,0,0],"GY1 1XA":[0,0,0,0,0,0,0,0],"GY1 1XB":[0,0,0,0,0,0,0,0],"GY1 1XD":[0,0,0,0,0,0,0,0],"GY1 1XE":[0,0,0,0,0,0,0,0],"GY1 1XF":[0,0,0,0,0,0,0,0],"GY1 1XG":[0,0,0,0,0,0,0,0],"GY1 1XH":[0,0,0,0,0,0,0,0],"GY1 1XJ":[0,0,0,0,0,0,0,0],"GY1 1XL":[0,0,0,0,0,0,0,0],"GY1 1XN":[0,0,0,0,0,0,0,0],"GY1 1XP":[0,0,0,0,0,0,0,0],"GY1 1XQ":[0,0,0,0,0,0,0,0],"GY1 1XR":[0,0,0,0,0,0,0,0],"GY1 1XS":[0,0,0,0,0,0,0,0],"GY1 1XT":[0,0,0,0,0,0,0,0],"GY1 1XU":[0,0,0,0,0,0,0,0],"GY1 1XW":[0,0,0,0,0,0,0,0],"GY1 1XX":[0,0,0,0,0,0,0,0],"GY1 1XY":[0,0,0,0,0,0,0,0],"GY1 1XZ":[0,0,0,0,0,0,0,0],"GY1 1YA":[0,0,0,0,0,0,0,0],"GY1 1YG":[0,0,0,0,0,0,0,0],"GY1 1YJ":[0,0,0,0,0,0,0,0],"GY1 1YL":[0,0,0,0,0,0,0,0],"GY1 1YN":[0,0,0,0,0,0,0,0],"GY1 1YP":[0,0,0,0,0,0,0,0],"GY1 1YQ":[0,0,0,0,0,0,0,0],"GY1 1YR":[0,0,0,0,0,0,0,0],"GY1 1YS":[0,0,0,0,0,0,0,0],"GY1 1YT":[0,0,0,0,0,0,0,0],"GY1 1YU":[0,0,0,0,0,0,0,0],"GY1 1YW":[0,0,0,0,0,0,0,0],"GY1 1YX":[0,0,0,0,0,0,0,0],"GY1 1YY":[0,0,0,0,0,0,0,0],"GY1 1YZ":[0,0,0,0,0,0,0,0],"GY1 1ZA":[0,0,0,0,0,0,0,0],"GY1 1ZB":[0,0,0,0,0,0,0,0],"GY1 1ZD":[0,0,0,0,0,0,0,0],"GY1 1ZE":[0,0,0,0,0,0,0,0],"GY1 1ZF":[0,0,0,0,0,0,0,0],"GY1 1ZG":[0,0,0,0,0,0,0,0],"GY1 1ZH":[0,0,0,0,0,0,0,0],"GY1 1ZL":[0,0,0,0,0,0,0,0],"GY1 1ZN":[0,0,0,0,0,0,0,0],"GY1 1ZP":[0,0,0,0,0,0,0,0],"GY1 1ZQ":[0,0,0,0,0,0,0,0],"GY1 1ZR":[0,0,0,0,0,0,0,0],"GY1 1ZS":[0,0,0,0,0,0,0,0],"GY1 1ZT":[0,0,0,0,0,0,0,0],"GY1 1ZU":[0,0,0,0,0,0,0,0],"GY1 1ZW":[0,0,0,0,0,0,0,0],"GY1 1ZX":[0,0,0,0,0,0,0,0],"GY1 1ZZ":[0,0,0,0,0,0,0,0]}}