{"headings":["oa11cd","lsoa11cd","msoa11cd","ladcd","lsoa11nm","msoa11nm","ladnm","ladnmw"],"values":[["E00166755","E00174772","E00008834","E00013428","E00176308","E00174770","E00013578","E00166759"],["E01032739","E01002704","E01033708","E01002726","E01000003"],["E02000001","E02000576","E02000371","E02000575"],["E09000001","E09000019","E09000012"],["City of London 001F","Islington 023D","Hackney 027G","Islington 022F","City of London 001C"],["City of London 001","Islington 023","Hackney 027","Islington 022"],["City of London","Islington","Hackney"],[""]],"data":{"EC2A 2AA":[0,0,0,0,0,0,0,0],"EC2A 2AB":[1,1,1,1,1,1,1,0],"EC2A 2AD":[2,2,2,2,2,2,2,0],"EC2A 2AE":[2,2,2,2,2,2,2,0],"EC2A 2AF":[0,0,0,0,0,0,0,0],"EC2A 2AG":[0,0,0,0,0,0,0,0],"EC2A 2AH":[3,1,1,1,1,1,1,0],"EC2A 2AJ":[2,2,2,2,2,2,2,0],"EC2A 2AL":[2,2,2,2,2,2,2,0],"EC2A 2AN":[4,2,2,2,2,2,2,0],"EC2A 2AP":[4,2,2,2,2,2,2,0],"EC2A 2AQ":[2,2,2,2,2,2,2,0],"EC2A 2AR":[2,2,2,2,2,2,2,0],"EC2A 2AS":[2,2,2,2,2,2,2,0],"EC2A 2AT":[0,0,0,0,0,0,0,0],"EC2A 2AU":[2,2,2,2,2,2,2,0],"EC2A 2AW":[2,2,2,2,2,2,2,0],"EC2A 2AX":[2,2,2,2,2,2,2,0],"EC2A 2AY":[5,1,1,1,1,1,1,0],"EC2A 2AZ":[2,2,2,2,2,2,2,0],"EC2A 2BA":[4,2,2,2,2,2,2,0],"EC2A 2BB":[3,1,1,1,1,1,1,0],"EC2A 2BD":[6,3,3,1,3,3,1,0],"EC2A 2BE":[4,2,2,2,2,2,2,0],"EC2A 2BF":[4,2,2,2,2,2,2,0],"EC2A 2BG":[4,2,2,2,2,2,2,0],"EC2A 2BH":[1,1,1,1,1,1,1,0],"EC2A 2BJ":[3,1,1,1,1,1,1,0],"EC2A 2BL":[2,2,2,2,2,2,2,0],"EC2A 2BN":[2,2,2,2,2,2,2,0],"EC2A 2BP":[4,2,2,2,2,2,2,0],"EC2A 2BQ":[0,0,0,0,0,0,0,0],"EC2A 2BR":[0,0,0,0,0,0,0,0],"EC2A 2BS":[2,2,2,2,2,2,2,0],"EC2A 2BT":[2,2,2,2,2,2,2,0],"EC2A 2BU":[2,2,2,2,2,2,2,0],"EC2A 2BW":[4,2,2,2,2,2,2,0],"EC2A 2BX":[2,2,2,2,2,2,2,0],"EC2A 2BY":[0,0,0,0,0,0,0,0],"EC2A 2BZ":[4,2,2,2,2,2,2,0],"EC2A 2DA":[0,0,0,0,0,0,0,0],"EC2A 2DB":[0,0,0,0,0,0,0,0],"EC2A 2DD":[6,3,3,1,3,3,1,0],"EC2A 2DE":[2,2,2,2,2,2,2,0],"EC2A 2DF":[4,2,2,2,2,2,2,0],"EC2A 2DG":[4,2,2,2,2,2,2,0],"EC2A 2DH":[2,2,2,2,2,2,2,0],"EC2A 2DJ":[2,2,2,2,2,2,2,0],"EC2A 2DL":[2,2,2,2,2,2,2,0],"EC2A 2DN":[3,1,1,1,1,1,1,0],"EC2A 2DP":[2,2,2,2,2,2,2,0],"EC2A 2DQ":[4,2,2,2,2,2,2,0],"EC2A 2DR":[5,1,1,1,1,1,1,0],"EC2A 2DS":[4,2,2,2,2,2,2,0],"EC2A 2DT":[1,1,1,1,1,1,1,0],"EC2A 2DU":[2,2,2,2,2,2,2,0],"EC2A 2DW":[1,1,1,1,1,1,1,0],"EC2A 2DX":[1,1,1,1,1,1,1,0],"EC2A 2DY":[1,1,1,1,1,1,1,0],"EC2A 2DZ":[2,2,2,2,2,2,2,0],"EC2A 2EA":[2,2,2,2,2,2,2,0],"EC2A 2EB":[0,0,0,0,0,0,0,0],"EC2A 2ED":[0,0,0,0,0,0,0,0],"EC2A 2EE":[4,2,2,2,2,2,2,0],"EC2A 2EF":[0,0,0,0,0,0,0,0],"EC2A 2EG":[0,0,0,0,0,0,0,0],"EC2A 2EH":[0,0,0,0,0,0,0,0],"EC2A 2EJ":[4,2,2,2,2,2,2,0],"EC2A 2EL":[2,2,2,2,2,2,2,0],"EC2A 2EN":[0,0,0,0,0,0,0,0],"EC2A 2EP":[3,1,1,1,1,1,1,0],"EC2A 2EQ":[2,2,2,2,2,2,2,0],"EC2A 2ER":[2,2,2,2,2,2,2,0],"EC2A 2ES":[0,0,0,0,0,0,0,0],"EC2A 2ET":[3,1,1,1,1,1,1,0],"EC2A 2EU":[3,1,1,1,1,1,1,0],"EC2A 2EW":[0,0,0,0,0,0,0,0],"EC2A 2EX":[0,0,0,0,0,0,0,0],"EC2A 2EY":[5,1,1,1,1,1,1,0],"EC2A 2EZ":[2,2,2,2,2,2,2,0],"EC2A 2FA":[4,2,2,2,2,2,2,0],"EC2A 2FB":[4,2,2,2,2,2,2,0],"EC2A 2FD":[4,2,2,2,2,2,2,0],"EC2A 2FE":[4,2,2,2,2,2,2,0],"EC2A 2FF":[4,2,2,2,2,2,2,0],"EC2A 2FG":[4,2,2,2,2,2,2,0],"EC2A 2FH":[2,2,2,2,2,2,2,0],"EC2A 2FJ":[4,2,2,2,2,2,2,0],"EC2A 2GU":[2,2,2,2,2,2,2,0],"EC2A 2HA":[6,3,3,1,3,3,1,0],"EC2A 2HB":[2,2,2,2,2,2,2,0],"EC2A 2HD":[2,2,2,2,2,2,2,0],"EC2A 2HE":[6,3,3,1,3,3,1,0],"EC2A 2HG":[4,2,2,2,2,2,2,0],"EC2A 2HH":[3,1,1,1,1,1,1,0],"EC2A 2HJ":[6,3,3,1,3,3,1,0],"EC2A 2HL":[4,2,2,2,2,2,2,0],"EC2A 2HN":[3,1,1,1,1,1,1,0],"EC2A 2HP":[5,1,1,1,1,1,1,0],"EC2A 2HQ":[0,0,0,0,0,0,0,0],"EC2A 2HR":[2,2,2,2,2,2,2,0],"EC2A 2HS":[0,0,0,0,0,0,0,0],"EC2A 2HT":[6,3,3,1,3,3,1,0],"EC2A 2HU":[6,3,3,1,3,3,1,0],"EC2A 2HX":[2,2,2,2,2,2,2,0],"EC2A 2HY":[2,2,2,2,2,2,2,0],"EC2A 2JA":[1,1,1,1,1,1,1,0],"EC2A 2JB":[2,2,2,2,2,2,2,0],"EC2A 2JD":[2,2,2,2,2,2,2,0],"EC2A 2JE":[2,2,2,2,2,2,2,0],"EC2A 2JH":[2,2,2,2,2,2,2,0],"EC2A 2JL":[0,0,0,0,0,0,0,0],"EC2A 2JN":[0,0,0,0,0,0,0,0],"EC2A 2JP":[6,3,3,1,3,3,1,0],"EC2A 2JR":[6,3,3,1,3,3,1,0],"EC2A 2JT":[2,2,2,2,2,2,2,0],"EC2A 2JX":[2,2,2,2,2,2,2,0],"EC2A 2LA":[1,1,1,1,1,1,1,0],"EC2A 2LB":[1,1,1,1,1,1,1,0],"EC2A 2LE":[2,2,2,2,2,2,2,0],"EC2A 2LH":[1,1,1,1,1,1,1,0],"EC2A 2LJ":[2,2,2,2,2,2,2,0],"EC2A 2LL":[7,4,0,0,4,0,0,0],"EC2A 2LN":[2,2,2,2,2,2,2,0],"EC2A 2LP":[6,3,3,1,3,3,1,0],"EC2A 2LQ":[2,2,2,2,2,2,2,0],"EC2A 2LT":[3,1,1,1,1,1,1,0],"EC2A 2LX":[4,2,2,2,2,2,2,0],"EC2A 2LY":[2,2,2,2,2,2,2,0],"EC2A 2NA":[2,2,2,2,2,2,2,0],"EC2A 2NB":[2,2,2,2,2,2,2,0],"EC2A 2ND":[7,4,0,0,4,0,0,0],"EC2A 2NE":[2,2,2,2,2,2,2,0],"EC2A 2NH":[2,2,2,2,2,2,2,0],"EC2A 2NJ":[2,2,2,2,2,2,2,0],"EC2A 2NL":[7,4,0,0,4,0,0,0],"EC2A 2NN":[0,0,0,0,0,0,0,0],"EC2A 2NP":[7,4,0,0,4,0,0,0],"EC2A 2NQ":[7,4,0,0,4,0,0,0],"EC2A 2NR":[0,0,0,0,0,0,0,0],"EC2A 2NS":[2,2,2,2,2,2,2,0],"EC2A 2NT":[0,0,0,0,0,0,0,0],"EC2A 2NU":[0,0,0,0,0,0,0,0],"EC2A 2NX":[0,0,0,0,0,0,0,0],"EC2A 2NY":[0,0,0,0,0,0,0,0],"EC2A 2PA":[6,3,3,1,3,3,1,0],"EC2A 2PB":[6,3,3,1,3,3,1,0],"EC2A 2PD":[2,2,2,2,2,2,2,0],"EC2A 2PE":[6,3,3,1,3,3,1,0],"EC2A 2PF":[6,3,3,1,3,3,1,0],"EC2A 2PG":[6,3,3,1,3,3,1,0],"EC2A 2PH":[6,3,3,1,3,3,1,0],"EC2A 2PP":[6,3,3,1,3,3,1,0],"EC2A 2PQ":[6,3,3,1,3,3,1,0],"EC2A 2PW":[2,2,2,2,2,2,2,0],"EC2A 2PX":[1,1,1,1,1,1,1,0],"EC2A 2RS":[0,0,0,0,0,0,0,0],"EC2A 2ST":[0,0,0,0,0,0,0,0],"EC2A 2UT":[0,0,0,0,0,0,0,0],"EC2A 2UU":[0,0,0,0,0,0,0,0],"EC2A 2WB":[0,0,0,0,0,0,0,0],"EC2A 2YF":[0,0,0,0,0,0,0,0]}}