{"headings":["oa11cd","lsoa11cd","msoa11cd","ladcd","lsoa11nm","msoa11nm","ladnm","ladnmw"],"values":[["E00166755","E00166757","E00013578"],["E01032739","E01002726"],["E02000001","E02000575"],["E09000001","E09000019"],["City of London 001F","Islington 022F"],["City of London 001","Islington 022"],["City of London","Islington"],[""]],"data":{"EC4R 2AT":[0,0,0,0,0,0,0,0],"EC4R 2BB":[0,0,0,0,0,0,0,0],"EC4R 2GA":[0,0,0,0,0,0,0,0],"EC4R 2GN":[0,0,0,0,0,0,0,0],"EC4R 2RA":[1,0,0,0,0,0,0,0],"EC4R 2RB":[1,0,0,0,0,0,0,0],"EC4R 2RD":[1,0,0,0,0,0,0,0],"EC4R 2RH":[0,0,0,0,0,0,0,0],"EC4R 2RL":[1,0,0,0,0,0,0,0],"EC4R 2RN":[1,0,0,0,0,0,0,0],"EC4R 2RP":[1,0,0,0,0,0,0,0],"EC4R 2RQ":[1,0,0,0,0,0,0,0],"EC4R 2RS":[1,0,0,0,0,0,0,0],"EC4R 2RT":[1,0,0,0,0,0,0,0],"EC4R 2RU":[1,0,0,0,0,0,0,0],"EC4R 2RX":[1,0,0,0,0,0,0,0],"EC4R 2SA":[1,0,0,0,0,0,0,0],"EC4R 2SB":[0,0,0,0,0,0,0,0],"EC4R 2SD":[1,0,0,0,0,0,0,0],"EC4R 2SE":[1,0,0,0,0,0,0,0],"EC4R 2SH":[0,0,0,0,0,0,0,0],"EC4R 2SJ":[1,0,0,0,0,0,0,0],"EC4R 2SL":[0,0,0,0,0,0,0,0],"EC4R 2SN":[1,0,0,0,0,0,0,0],"EC4R 2SP":[0,0,0,0,0,0,0,0],"EC4R 2SR":[1,0,0,0,0,0,0,0],"EC4R 2SS":[0,0,0,0,0,0,0,0],"EC4R 2ST":[0,0,0,0,0,0,0,0],"EC4R 2SU":[0,0,0,0,0,0,0,0],"EC4R 2SW":[1,0,0,0,0,0,0,0],"EC4R 2SX":[0,0,0,0,0,0,0,0],"EC4R 2SY":[1,0,0,0,0,0,0,0],"EC4R 2TD":[1,0,0,0,0,0,0,0],"EC4R 2TE":[1,0,0,0,0,0,0,0],"EC4R 2TH":[0,0,0,0,0,0,0,0],"EC4R 2TJ":[1,0,0,0,0,0,0,0],"EC4R 2TL":[2,1,1,1,1,1,1,0],"EC4R 2TQ":[1,0,0,0,0,0,0,0],"EC4R 2TR":[1,0,0,0,0,0,0,0],"EC4R 2WQ":[2,1,1,1,1,1,1,0],"EC4R 2YA":[0,0,0,0,0,0,0,0],"EC4R 2YB":[0,0,0,0,0,0,0,0]}}